evmos_protobuf/.gitignore
evmos_protobuf/__init__.py
evmos_protobuf/__init__.pyi
evmos_protobuf/proofs.proto
evmos_protobuf/proofs_pb2.py
evmos_protobuf/proofs_pb2.pyi
evmos_protobuf/cosmos/__init__.py
evmos_protobuf/cosmos/__init__.pyi
evmos_protobuf/cosmos/app/__init__.py
evmos_protobuf/cosmos/app/__init__.pyi
evmos_protobuf/cosmos/app/module/__init__.py
evmos_protobuf/cosmos/app/module/__init__.pyi
evmos_protobuf/cosmos/app/module/v1alpha1/__init__.py
evmos_protobuf/cosmos/app/module/v1alpha1/__init__.pyi
evmos_protobuf/cosmos/app/module/v1alpha1/module.proto
evmos_protobuf/cosmos/app/module/v1alpha1/module_pb2.py
evmos_protobuf/cosmos/app/module/v1alpha1/module_pb2.pyi
evmos_protobuf/cosmos/app/v1alpha1/__init__.py
evmos_protobuf/cosmos/app/v1alpha1/__init__.pyi
evmos_protobuf/cosmos/app/v1alpha1/config.proto
evmos_protobuf/cosmos/app/v1alpha1/config_pb2.py
evmos_protobuf/cosmos/app/v1alpha1/config_pb2.pyi
evmos_protobuf/cosmos/app/v1alpha1/module.proto
evmos_protobuf/cosmos/app/v1alpha1/module_pb2.py
evmos_protobuf/cosmos/app/v1alpha1/module_pb2.pyi
evmos_protobuf/cosmos/app/v1alpha1/query.proto
evmos_protobuf/cosmos/app/v1alpha1/query_pb2.py
evmos_protobuf/cosmos/app/v1alpha1/query_pb2.pyi
evmos_protobuf/cosmos/app/v1alpha1/query_pb2_grpc.py
evmos_protobuf/cosmos/auth/__init__.py
evmos_protobuf/cosmos/auth/__init__.pyi
evmos_protobuf/cosmos/auth/v1beta1/__init__.py
evmos_protobuf/cosmos/auth/v1beta1/__init__.pyi
evmos_protobuf/cosmos/auth/v1beta1/auth.proto
evmos_protobuf/cosmos/auth/v1beta1/auth_pb2.py
evmos_protobuf/cosmos/auth/v1beta1/auth_pb2.pyi
evmos_protobuf/cosmos/auth/v1beta1/genesis.proto
evmos_protobuf/cosmos/auth/v1beta1/genesis_pb2.py
evmos_protobuf/cosmos/auth/v1beta1/genesis_pb2.pyi
evmos_protobuf/cosmos/auth/v1beta1/query.proto
evmos_protobuf/cosmos/auth/v1beta1/query_pb2.py
evmos_protobuf/cosmos/auth/v1beta1/query_pb2.pyi
evmos_protobuf/cosmos/auth/v1beta1/query_pb2_grpc.py
evmos_protobuf/cosmos/authz/__init__.py
evmos_protobuf-0.2.0.dist-info/METADATA
evmos_protobuf-0.2.0.dist-info/WHEEL
evmos_protobuf-0.2.0.dist-info/RECORD
