Metadata-Version: 2.1
Name: evmos_protobuf
Version: 0.2.0
Summary: This package contains a compiled python version of all evmos protobuf files with their dependencies
Project-URL: Homepage, https://github.com/ctrl-Felix/cosmospy-protobuf/
Project-URL: Bug Tracker, https://github.com/ctrl-Felix/cosmospy-protobuf/issues
Project-URL: Changelog, https://github.com/ctrl-Felix/cosmospy-protobuf/blob/chain/evmos/CHANGELOG.md
Author-email: ctrl-felix <dev@ctrl-felix.de>
License: BSD 3-Clause License
Keywords: cosmospy,cosmospy-protobuf,evmos,evmos-protobuf,evmospy,osmospy,proto,protobuf
Classifier: Operating System :: OS Independent
Classifier: Programming Language :: Python :: 3
Requires-Dist: protobuf
